{
  "easy": {
    "איל": "מבעלי הקרניים",
    "צבי": "בעל חיים ממשפחת הפריים",
    "כלב": "סוג של חיית בית – חיית מחמד",
    "נשר": "עוף דורס",
    "פרה": "בעל חיים ממשפחת הפריים",
    "יען": "עוף גדול",
    "נמר": "מין טורף",
    "זאב": "מין טורף",
    "גמל": "ספינת המדבר",
    "פיל": "יונק גדול וכבד בעל חדק ארוך",
    "גדי": "סוג של עז בר",
    "יעל": "בעל חיים ממשפחת הפריים",
    "שור": "בעל חיים ממשפחת הפריים"
  },
  "medium": {
    "ראם": "בעל חיים ממשפחת הפריים",
    "תאו": "בעל חיים ממשפחת הפריים",
    "יאק": "בעל חיים ממשפחת הפריים",
    "שפן": "מכרסם קטן",
    "שחף": "סוג של עוף מים",
    "עיט": "עוף דורס",
    "זחל": "מגלגולי השפירית",
    "תיש": "סוג של עז בר",
    "מקק": "מין חרק",
    "חגב": "מין חרק",
    "כוח": "מן לטאה",
    "גדי": "סוג של עז בר",
    "למה": "גמל חסר דבשת",
    "דוב": "חיית טרף גדולה",
    "גוק": "מין חרק",
    "כבש": "בעל חיים ממשפחת הפריים"
  },
  "hard": {
    "ליש": "מין טורף",
    "גנו": "בעל חיים צמחוני",
    "חדף": "סוג של יונק",
    "סרו": "בעל חיים ממשפחת הפריים",
    "דיה": "עוף דורס",
    "רחם": "עוף דורס",
    "אמו": "סוג של עוף – מין עוף",
    "פנק": "מין טורף",
    "כפן": "עוף ביצה",
    "פתן": "מין נחש",
    "צפע": "מין נחש",
    "עכן": "מין נחש",
    "פאג": "גזע כלבים",
    "סיס": "ציפור שיר קטנה",
    "נקר": "סוג של ציפור שיר",
    "דרן": "זחל גלילי",
    "קוי": "סוג של דג",
    "נון": "דג ממשפחת הקרפיונים",
    "חפף": "מין דג קטן, דג ים קטן",
    "קוד": "מין דג קטן",
    "ארה": "מין תוכי",
    "פרא": "חמור בר טיבטי",
    "תחש": "גזע כלבים",
    "בסט": "סוג של כלב",
    "קדו": "מין תוכי",
    "עקב": "עוף דורס",
    "שלך": "עוף דורס",
    "דאה": "עוף דורס",
    "אוח": "עוף דורס",
    "פרס": "עוף דורס",
    "פרש": "סוג של קוף",
    "אוז": "סוג של עוף מים",
    "קאק": "ציפור שיר",
    "טגו": "מן לטאה",
    "גקו": "מן לטאה",
    "דלק": "טורף קטן",
    "קטה": "סוג של עוף – מין עוף",
    "שלו": "סוג של עוף – מין עוף",
    "אשף": "מין עטלף – מיני עטלפים",
    "קגו": "סוג של עוף – מין עוף",
    "תור": "סוג של עוף – מין עוף",
    "כחל": "סוג של עוף – מין עוף",
    "זקו": "מין תוכי",
    "דקר": "סוג דג מאכל – דגי מאכל",
    "סול": "סוג של דג",
    "יון": "סוג של עוף – מין עוף",
    "אלק": "מן אייל",
    "בקה": "מן יתוש",
    "אדס": "מן יתוש",
    "טבן": "מן זבוב",
    "גחן": "מין טורף",
    "זבד": "מין טורף",
    "שרף": "מין נחש",
    "חנק": "מין נחש",
    "עיר": "צאצא החמור",
    "טטו": "סוג של ארמדיל",
    "סגא": "חרק טורף",
    "רצה": "חרק טורף",
    "אקו": "סוג של עז בר",
    "קרס": "דג ממשפחת הקרפיונים",
    "לקס": "דג מאכל, סלמון",
    "חפפ": "מין דג קטן",
    "זבו": "בעל חיים ממשפחת הפריים",
    "שיה": "כבשה צעירה",
    "נטה": "מין ברווז",
    "אסף": "גזע כבשים",
    "טסל": "גזע כבשים",
    "באס": "סוג של דג",
    "פדט": "סוג של מכרסם",
    "איה": "עוף דורס",
    "טפס": "ציפור שיר קטנה",
    "תנר": "ציפור שיר",
    "תפר": "ציפור שיר",
    "טרד": "ציפור שיר"
  }
}
